mdul/__init__.py
mdul/main.py
mdul/test_mdul.py
mdul-0.0.2.dist-info/LICENSE
mdul-0.0.2.dist-info/METADATA
mdul-0.0.2.dist-info/WHEEL
mdul-0.0.2.dist-info/entry_points.txt
mdul-0.0.2.dist-info/top_level.txt
mdul-0.0.2.dist-info/RECORD
