Metadata-Version: 2.1
Name: mdul
Version: 0.0.2
Summary: An utility to upload local images in markdown to sm.ms and convert markdown file correspondingly.
Home-page: https://github.com/crh19970307/mdul
Author: Ruiheng Chang
Author-email: rhchang@pku.edu.cn
License: MIT
Keywords: markdown image upload convert
Platform: UNKNOWN
Requires-Python: >=3.4
Requires-Dist: requests
Provides-Extra: test
Requires-Dist: mock (>=2.0.0) ; extra == 'test'
Requires-Dist: pytest (<5.0) ; extra == 'test'
